askbot_slack/__init__.py
askbot_slack/conf.py
askbot_slack-0.2.0.dist-info/DESCRIPTION.rst
askbot_slack-0.2.0.dist-info/METADATA
askbot_slack-0.2.0.dist-info/metadata.json
askbot_slack-0.2.0.dist-info/pbr.json
askbot_slack-0.2.0.dist-info/RECORD
askbot_slack-0.2.0.dist-info/top_level.txt
askbot_slack-0.2.0.dist-info/WHEEL
