Metadata-Version: 2.0
Name: askbot-slack
Version: 0.2.0
Summary: Simple Slack integration for Askbot.
Home-page: https://github.com/jonmbake/askbot-slack
Author: Jon Bake
Author-email: jonmbake@gmail.com
License: MIT
Keywords: askbot slack integration
Platform: UNKNOWN
Classifier: Development Status :: 5 - Production/Stable
Classifier: Intended Audience :: Developers
Classifier: Programming Language :: Python :: 2
Classifier: Programming Language :: Python :: 2.6
Classifier: Programming Language :: Python :: 2.7
Requires-Dist: askbot
Requires-Dist: requests
